[
  {
    "key": "65242b56ad591f1bc6f52ecb",
    "nombre": "Facturación"
  },
  {
    "key": "65242b56ad591f1bc6f52ecc",
    "nombre": "Contabilidad"
  },
  {
    "key": "65242b56ad591f1bc6f52ecd",
    "nombre": "Administración"
  },
  {
    "key": "65242b56ad591f1bc6f52ece",
    "nombre": "Compras"
  },
  {
    "key": "65242b56ad591f1bc6f52ecf",
    "nombre": "Gestion humana"
  },
  {
    "key": "65242b56ad591f1bc6f52ed0",
    "nombre": "Inventarios"
  },
  {
    "key": "65242b56ad591f1bc6f52ed1",
    "nombre": "Triburos"
  },
  {
    "key": "65242b56ad591f1bc6f52ed2",
    "nombre": "Usuarios"
  }
]